{"prefix":"140","children":{"0":{"prefix":"1400","depth":4,"pinCount":1,"mappedCount":1,"children":{"0":{"prefix":"14000","depth":5,"pinCount":1,"mappedCount":1,"children":{"1":{"prefix":"140001","depth":6,"pinCount":1,"mappedCount":1}}}}},"1":{"prefix":"1401","depth":4,"pinCount":22,"mappedCount":22,"children":{"0":{"prefix":"14010","depth":5,"pinCount":5,"mappedCount":5,"children":{"1":{"prefix":"140101","depth":6,"pinCount":1,"mappedCount":1},"2":{"prefix":"140102","depth":6,"pinCount":1,"mappedCount":1},"3":{"prefix":"140103","depth":6,"pinCount":1,"mappedCount":1},"8":{"prefix":"140108","depth":6,"pinCount":1,"mappedCount":1},"9":{"prefix":"140109","depth":6,"pinCount":1,"mappedCount":1}}},"1":{"prefix":"14011","depth":5,"pinCount":10,"mappedCount":10,"children":{"0":{"prefix":"140110","depth":6,"pinCount":1,"mappedCount":1},"1":{"prefix":"140111","depth":6,"pinCount":1,"mappedCount":1},"2":{"prefix":"140112","depth":6,"pinCount":1,"mappedCount":1},"3":{"prefix":"140113","depth":6,"pinCount":1,"mappedCount":1},"4":{"prefix":"140114","depth":6,"pinCount":1,"mappedCount":1},"5":{"prefix":"140115","depth":6,"pinCount":1,"mappedCount":1},"6":{"prefix":"140116","depth":6,"pinCount":1,"mappedCount":1},"7":{"prefix":"140117","depth":6,"pinCount":1,"mappedCount":1},"8":{"prefix":"140118","depth":6,"pinCount":1,"mappedCount":1},"9":{"prefix":"140119","depth":6,"pinCount":1,"mappedCount":1}}},"2":{"prefix":"14012","depth":5,"pinCount":6,"mappedCount":6,"children":{"3":{"prefix":"140123","depth":6,"pinCount":1,"mappedCount":1},"4":{"prefix":"140124","depth":6,"pinCount":1,"mappedCount":1},"5":{"prefix":"140125","depth":6,"pinCount":1,"mappedCount":1},"6":{"prefix":"140126","depth":6,"pinCount":1,"mappedCount":1},"7":{"prefix":"140127","depth":6,"pinCount":1,"mappedCount":1},"8":{"prefix":"140128","depth":6,"pinCount":1,"mappedCount":1}}},"3":{"prefix":"14013","depth":5,"pinCount":1,"mappedCount":1,"children":{"3":{"prefix":"140133","depth":6,"pinCount":1,"mappedCount":1}}}}},"2":{"prefix":"1402","depth":4,"pinCount":1,"mappedCount":1,"children":{"0":{"prefix":"14020","depth":5,"pinCount":1,"mappedCount":1,"children":{"1":{"prefix":"140201","depth":6,"pinCount":1,"mappedCount":1}}}}},"3":{"prefix":"1403","depth":4,"pinCount":4,"mappedCount":4,"children":{"0":{"prefix":"14030","depth":5,"pinCount":4,"mappedCount":4,"children":{"1":{"prefix":"140301","depth":6,"pinCount":1,"mappedCount":1},"6":{"prefix":"140306","depth":6,"pinCount":1,"mappedCount":1},"7":{"prefix":"140307","depth":6,"pinCount":1,"mappedCount":1},"8":{"prefix":"140308","depth":6,"pinCount":1,"mappedCount":1}}}}},"4":{"prefix":"1404","depth":4,"pinCount":9,"mappedCount":9,"children":{"0":{"prefix":"14040","depth":5,"pinCount":6,"mappedCount":6,"children":{"1":{"prefix":"140401","depth":6,"pinCount":1,"mappedCount":1},"2":{"prefix":"140402","depth":6,"pinCount":1,"mappedCount":1},"5":{"prefix":"140405","depth":6,"pinCount":1,"mappedCount":1},"6":{"prefix":"140406","depth":6,"pinCount":1,"mappedCount":1},"7":{"prefix":"140407","depth":6,"pinCount":1,"mappedCount":1},"8":{"prefix":"140408","depth":6,"pinCount":1,"mappedCount":1}}},"1":{"prefix":"14041","depth":5,"pinCount":3,"mappedCount":3,"children":{"2":{"prefix":"140412","depth":6,"pinCount":1,"mappedCount":1},"3":{"prefix":"140413","depth":6,"pinCount":1,"mappedCount":1},"7":{"prefix":"140417","depth":6,"pinCount":1,"mappedCount":1}}}}},"5":{"prefix":"1405","depth":4,"pinCount":3,"mappedCount":3,"children":{"0":{"prefix":"14050","depth":5,"pinCount":3,"mappedCount":3,"children":{"1":{"prefix":"140501","depth":6,"pinCount":1,"mappedCount":1},"6":{"prefix":"140506","depth":6,"pinCount":1,"mappedCount":1},"7":{"prefix":"140507","depth":6,"pinCount":1,"mappedCount":1}}}}},"6":{"prefix":"1406","depth":4,"pinCount":4,"mappedCount":4,"children":{"0":{"prefix":"14060","depth":5,"pinCount":4,"mappedCount":4,"children":{"1":{"prefix":"140601","depth":6,"pinCount":1,"mappedCount":1},"2":{"prefix":"140602","depth":6,"pinCount":1,"mappedCount":1},"3":{"prefix":"140603","depth":6,"pinCount":1,"mappedCount":1},"4":{"prefix":"140604","depth":6,"pinCount":1,"mappedCount":1}}}}},"7":{"prefix":"1407","depth":4,"pinCount":2,"mappedCount":2,"children":{"0":{"prefix":"14070","depth":5,"pinCount":2,"mappedCount":2,"children":{"1":{"prefix":"140701","depth":6,"pinCount":1,"mappedCount":1},"2":{"prefix":"140702","depth":6,"pinCount":1,"mappedCount":1}}}}},"8":{"prefix":"1408","depth":4,"pinCount":1,"mappedCount":1,"children":{"0":{"prefix":"14080","depth":5,"pinCount":1,"mappedCount":1,"children":{"2":{"prefix":"140802","depth":6,"pinCount":1,"mappedCount":1}}}}},"9":{"prefix":"1409","depth":4,"pinCount":1,"mappedCount":1,"children":{"0":{"prefix":"14090","depth":5,"pinCount":1,"mappedCount":1,"children":{"1":{"prefix":"140901","depth":6,"pinCount":1,"mappedCount":1}}}}}}}