{"prefix":"262","children":{"0":{"prefix":"2620","depth":4,"pinCount":1,"mappedCount":1,"children":{"0":{"prefix":"26200","depth":5,"pinCount":1,"mappedCount":1,"children":{"1":{"prefix":"262001","depth":6,"pinCount":1,"mappedCount":1}}}}},"1":{"prefix":"2621","depth":4,"pinCount":4,"mappedCount":4,"children":{"2":{"prefix":"26212","depth":5,"pinCount":4,"mappedCount":4,"children":{"1":{"prefix":"262121","depth":6,"pinCount":1,"mappedCount":1},"2":{"prefix":"262122","depth":6,"pinCount":1,"mappedCount":1},"3":{"prefix":"262123","depth":6,"pinCount":1,"mappedCount":1},"4":{"prefix":"262124","depth":6,"pinCount":1,"mappedCount":1}}}}},"2":{"prefix":"2622","depth":4,"pinCount":3,"mappedCount":3,"children":{"0":{"prefix":"26220","depth":5,"pinCount":3,"mappedCount":3,"children":{"1":{"prefix":"262201","depth":6,"pinCount":1,"mappedCount":1},"2":{"prefix":"262202","depth":6,"pinCount":1,"mappedCount":1},"3":{"prefix":"262203","depth":6,"pinCount":1,"mappedCount":1}}}}},"3":{"prefix":"2623","depth":4,"pinCount":6,"mappedCount":6,"children":{"0":{"prefix":"26230","depth":5,"pinCount":4,"mappedCount":4,"children":{"2":{"prefix":"262302","depth":6,"pinCount":1,"mappedCount":1},"5":{"prefix":"262305","depth":6,"pinCount":1,"mappedCount":1},"8":{"prefix":"262308","depth":6,"pinCount":1,"mappedCount":1},"9":{"prefix":"262309","depth":6,"pinCount":1,"mappedCount":1}}},"1":{"prefix":"26231","depth":5,"pinCount":2,"mappedCount":2,"children":{"0":{"prefix":"262310","depth":6,"pinCount":1,"mappedCount":1},"1":{"prefix":"262311","depth":6,"pinCount":1,"mappedCount":1}}}}},"4":{"prefix":"2624","depth":4,"pinCount":4,"mappedCount":4,"children":{"0":{"prefix":"26240","depth":5,"pinCount":4,"mappedCount":4,"children":{"1":{"prefix":"262401","depth":6,"pinCount":1,"mappedCount":1},"2":{"prefix":"262402","depth":6,"pinCount":1,"mappedCount":1},"5":{"prefix":"262405","depth":6,"pinCount":1,"mappedCount":1},"6":{"prefix":"262406","depth":6,"pinCount":1,"mappedCount":1}}}}},"5":{"prefix":"2625","depth":4,"pinCount":35,"mappedCount":35,"children":{"0":{"prefix":"26250","depth":5,"pinCount":2,"mappedCount":2,"children":{"1":{"prefix":"262501","depth":6,"pinCount":1,"mappedCount":1},"2":{"prefix":"262502","depth":6,"pinCount":1,"mappedCount":1}}},"2":{"prefix":"26252","depth":5,"pinCount":10,"mappedCount":10,"children":{"0":{"prefix":"262520","depth":6,"pinCount":1,"mappedCount":1},"1":{"prefix":"262521","depth":6,"pinCount":1,"mappedCount":1},"2":{"prefix":"262522","depth":6,"pinCount":1,"mappedCount":1},"3":{"prefix":"262523","depth":6,"pinCount":1,"mappedCount":1},"4":{"prefix":"262524","depth":6,"pinCount":1,"mappedCount":1},"5":{"prefix":"262525","depth":6,"pinCount":1,"mappedCount":1},"6":{"prefix":"262526","depth":6,"pinCount":1,"mappedCount":1},"7":{"prefix":"262527","depth":6,"pinCount":1,"mappedCount":1},"8":{"prefix":"262528","depth":6,"pinCount":1,"mappedCount":1},"9":{"prefix":"262529","depth":6,"pinCount":1,"mappedCount":1}}},"3":{"prefix":"26253","depth":5,"pinCount":5,"mappedCount":5,"children":{"0":{"prefix":"262530","depth":6,"pinCount":1,"mappedCount":1},"1":{"prefix":"262531","depth":6,"pinCount":1,"mappedCount":1},"2":{"prefix":"262532","depth":6,"pinCount":1,"mappedCount":1},"3":{"prefix":"262533","depth":6,"pinCount":1,"mappedCount":1},"4":{"prefix":"262534","depth":6,"pinCount":1,"mappedCount":1}}},"4":{"prefix":"26254","depth":5,"pinCount":8,"mappedCount":8,"children":{"0":{"prefix":"262540","depth":6,"pinCount":1,"mappedCount":1},"1":{"prefix":"262541","depth":6,"pinCount":1,"mappedCount":1},"2":{"prefix":"262542","depth":6,"pinCount":1,"mappedCount":1},"3":{"prefix":"262543","depth":6,"pinCount":1,"mappedCount":1},"4":{"prefix":"262544","depth":6,"pinCount":1,"mappedCount":1},"5":{"prefix":"262545","depth":6,"pinCount":1,"mappedCount":1},"6":{"prefix":"262546","depth":6,"pinCount":1,"mappedCount":1},"7":{"prefix":"262547","depth":6,"pinCount":1,"mappedCount":1}}},"5":{"prefix":"26255","depth":5,"pinCount":6,"mappedCount":6,"children":{"0":{"prefix":"262550","depth":6,"pinCount":1,"mappedCount":1},"1":{"prefix":"262551","depth":6,"pinCount":1,"mappedCount":1},"2":{"prefix":"262552","depth":6,"pinCount":1,"mappedCount":1},"3":{"prefix":"262553","depth":6,"pinCount":1,"mappedCount":1},"4":{"prefix":"262554","depth":6,"pinCount":1,"mappedCount":1},"5":{"prefix":"262555","depth":6,"pinCount":1,"mappedCount":1}}},"6":{"prefix":"26256","depth":5,"pinCount":1,"mappedCount":1,"children":{"1":{"prefix":"262561","depth":6,"pinCount":1,"mappedCount":1}}},"7":{"prefix":"26257","depth":5,"pinCount":2,"mappedCount":2,"children":{"2":{"prefix":"262572","depth":6,"pinCount":1,"mappedCount":1},"6":{"prefix":"262576","depth":6,"pinCount":1,"mappedCount":1}}},"8":{"prefix":"26258","depth":5,"pinCount":1,"mappedCount":1,"children":{"0":{"prefix":"262580","depth":6,"pinCount":1,"mappedCount":1}}}}},"7":{"prefix":"2627","depth":4,"pinCount":10,"mappedCount":10,"children":{"0":{"prefix":"26270","depth":5,"pinCount":2,"mappedCount":2,"children":{"1":{"prefix":"262701","depth":6,"pinCount":1,"mappedCount":1},"2":{"prefix":"262702","depth":6,"pinCount":1,"mappedCount":1}}},"2":{"prefix":"26272","depth":5,"pinCount":8,"mappedCount":8,"children":{"1":{"prefix":"262721","depth":6,"pinCount":1,"mappedCount":1},"2":{"prefix":"262722","depth":6,"pinCount":1,"mappedCount":1},"3":{"prefix":"262723","depth":6,"pinCount":1,"mappedCount":1},"4":{"prefix":"262724","depth":6,"pinCount":1,"mappedCount":1},"5":{"prefix":"262725","depth":6,"pinCount":1,"mappedCount":1},"6":{"prefix":"262726","depth":6,"pinCount":1,"mappedCount":1},"7":{"prefix":"262727","depth":6,"pinCount":1,"mappedCount":1},"8":{"prefix":"262728","depth":6,"pinCount":1,"mappedCount":1}}}}},"8":{"prefix":"2628","depth":4,"pinCount":5,"mappedCount":5,"children":{"0":{"prefix":"26280","depth":5,"pinCount":5,"mappedCount":5,"children":{"1":{"prefix":"262801","depth":6,"pinCount":1,"mappedCount":1},"2":{"prefix":"262802","depth":6,"pinCount":1,"mappedCount":1},"3":{"prefix":"262803","depth":6,"pinCount":1,"mappedCount":1},"4":{"prefix":"262804","depth":6,"pinCount":1,"mappedCount":1},"5":{"prefix":"262805","depth":6,"pinCount":1,"mappedCount":1}}}}},"9":{"prefix":"2629","depth":4,"pinCount":8,"mappedCount":8,"children":{"0":{"prefix":"26290","depth":5,"pinCount":8,"mappedCount":8,"children":{"1":{"prefix":"262901","depth":6,"pinCount":1,"mappedCount":1},"2":{"prefix":"262902","depth":6,"pinCount":1,"mappedCount":1},"3":{"prefix":"262903","depth":6,"pinCount":1,"mappedCount":1},"4":{"prefix":"262904","depth":6,"pinCount":1,"mappedCount":1},"5":{"prefix":"262905","depth":6,"pinCount":1,"mappedCount":1},"6":{"prefix":"262906","depth":6,"pinCount":1,"mappedCount":1},"7":{"prefix":"262907","depth":6,"pinCount":1,"mappedCount":1},"8":{"prefix":"262908","depth":6,"pinCount":1,"mappedCount":1}}}}}}}