{"prefix":"79","pins":[{"pin":"790001","district":"WEST KAMENG","state":"ARUNACHAL PRADESH","offices":["Nafra B.O","Rahung B.O","Salari B.O"],"officeCount":5},{"pin":"790002","district":"WEST KAMENG","state":"ARUNACHAL PRADESH","offices":["Balemu B.O","Tenzingaon B.O","Kalaktang S.O"],"officeCount":3},{"pin":"790003","district":"WEST KAMENG","state":"ARUNACHAL PRADESH","offices":["Jigaon","Shergaon B.O","Rupa S.O"],"officeCount":3},{"pin":"790101","district":"WEST KAMENG","state":"ARUNACHAL PRADESH","offices":["Dirang S.O","Lish B.O","Sangti B.O"],"officeCount":6},{"pin":"790102","district":"EAST KAMENG","state":"ARUNACHAL PRADESH","offices":["Bameng B.O","Lada B.O","Pipu-dipu B.O"],"officeCount":98},{"pin":"790103","district":"PAKKE KESSANG","state":"ARUNACHAL PRADESH","offices":["Khari","Gumte","Keko"],"officeCount":18},{"pin":"790104","district":"TAWANG","state":"ARUNACHAL PRADESH","offices":["Sakpret B.O","8 K.M. Labour Camp","Shyo"],"officeCount":12},{"pin":"790105","district":"TAWANG","state":"ARUNACHAL PRADESH","offices":["Lhou B.O","Mukto B.O","Jang S.O"],"officeCount":5},{"pin":"790106","district":"TAWANG","state":"ARUNACHAL PRADESH","offices":["Gispu B.O","Mangnam","Yabab"],"officeCount":9},{"pin":"790114","district":"WEST KAMENG","state":"ARUNACHAL PRADESH","offices":["Elephant Flat","Sessa","Upper Bhalukpong HQ"],"officeCount":11},{"pin":"790116","district":"WEST KAMENG","state":"ARUNACHAL PRADESH","offices":["Kimi Village","Dahung B.O","Thessa"],"officeCount":12},{"pin":"791001","district":"WEST SIANG","state":"ARUNACHAL PRADESH","offices":["Bagra B.O","Darak B.O","Kaying B.O"],"officeCount":49},{"pin":"791002","district":"UPPER SIANG","state":"ARUNACHAL PRADESH","offices":["Palling H.Q.","Janbo","Mariyang B.O"],"officeCount":24},{"pin":"791003","district":"SHI YOMI","state":"ARUNACHAL PRADESH","offices":["Rapum","Geching","Pidi H.Q."],"officeCount":12},{"pin":"791004","district":"EAST SIANG","state":"ARUNACHAL PRADESH","offices":["Babuk","BOLENG SO"],"officeCount":2},{"pin":"791101","district":"LEPARADA","state":"ARUNACHAL PRADESH","offices":["Bame B.O","Zirdo","Dali B.O"],"officeCount":15},{"pin":"791102","district":"EAST SIANG","state":"ARUNACHAL PRADESH","offices":["Ledum B.O","Riga B.O","Niglok"],"officeCount":29},{"pin":"791103","district":"EAST SIANG","state":"ARUNACHAL PRADESH","offices":["Komsing(Karo)","Lissing","Yibuk"],"officeCount":17},{"pin":"791104","district":"EAST SIANG","state":"ARUNACHAL PRADESH","offices":["Silluk B.O","Mebo S.O","Borguli B.O"],"officeCount":10},{"pin":"791105","district":"UPPER SIANG","state":"ARUNACHAL PRADESH","offices":["Ningging","Nyokong","Gette"],"officeCount":18},{"pin":"791109","district":"PAPUM PARE","state":"ARUNACHAL PRADESH","offices":["Nirjuli S.O"],"officeCount":1},{"pin":"791110","district":"PAPUM PARE","state":"ARUNACHAL PRADESH","offices":["Naharlagun S.O","Model Village B.O","Yupia B.O"],"officeCount":3},{"pin":"791111","district":"PAPUM PARE","state":"ARUNACHAL PRADESH","offices":["Arunachal Pradesh Secretariat S.O","Itanagar H.O"],"officeCount":2},{"pin":"791112","district":"PAPUM PARE","state":"ARUNACHAL PRADESH","offices":["Khyate","Totpu - I","Doimukh S.O"],"officeCount":19},{"pin":"791113","district":"PAPUM PARE","state":"ARUNACHAL PRADESH","offices":["Bormai","JULLY B.O","Rakap"],"officeCount":21},{"pin":"791114","district":"PAPUM PARE","state":"ARUNACHAL PRADESH","offices":["De - Dolo","Bobia","Ressing"],"officeCount":13},{"pin":"791118","district":"KURUNG KUMEY","state":"ARUNACHAL PRADESH","offices":["Joru","Ribung (Nguri)","Lenko"],"officeCount":149},{"pin":"791119","district":"LOWER SUBANSIRI","state":"ARUNACHAL PRADESH","offices":["Yazali B.O","Silsango","Lekang"],"officeCount":14},{"pin":"791120","district":"LOWER SUBANSIRI","state":"ARUNACHAL PRADESH","offices":["Old Ziro B.O","Talo B.O","RAKA B.O"],"officeCount":43},{"pin":"791121","district":"PAPUM PARE","state":"ARUNACHAL PRADESH","offices":["Kimin S.O","Hawa Camp B.O","Lora - I & II"],"officeCount":3},{"pin":"791122","district":"UPPER SUBANSIRI","state":"ARUNACHAL PRADESH","offices":["Maro B.O","Sippi B.O","Ishneya(Isnia) I"],"officeCount":153},{"pin":"791123","district":"PAPUM PARE","state":"ARUNACHAL PRADESH","offices":["Kokila B.O","Lanka","Hollongi Chariali"],"officeCount":16},{"pin":"791125","district":"LOWER SIANG","state":"ARUNACHAL PRADESH","offices":["Taramori","Durpai","Hime"],"officeCount":31},{"pin":"791701","district":"AIZAWL","state":"MIZORAM","offices":["HLUMTE","S. LUNGDAI","CHITHAR"],"officeCount":4},{"pin":"792001","district":"LOHIT","state":"ARUNACHAL PRADESH","offices":["Changliang B.O","Loiliang B.O","Danglat"],"officeCount":22},{"pin":"792055","district":"CHANGLANG","state":"ARUNACHAL PRADESH","offices":["Two-hat B.O","Gandhigram B.O"],"officeCount":2},{"pin":"792056","district":"CHANGLANG","state":"ARUNACHAL PRADESH","offices":["New Mohang B.O","Rajanagar B.O","Bordumsa S.O"],"officeCount":6},{"pin":"792101","district":"DIBANG VALLEY","state":"ARUNACHAL PRADESH","offices":["Aiso","Anini S.O","Alinye B.O"],"officeCount":5},{"pin":"792102","district":"NAMSAI","state":"ARUNACHAL PRADESH","offices":["Chowkham S.O","Wakro B.O","Kamlang Nagar B.O"],"officeCount":8},{"pin":"792103","district":"NAMSAI","state":"ARUNACHAL PRADESH","offices":["Nanam B.O","Udaipur B.O","Wingko B.O"],"officeCount":27},{"pin":"792104","district":"ANJAW","state":"ARUNACHAL PRADESH","offices":["Chaglagam B.O","Wallong B.O","Kaho"],"officeCount":53},{"pin":"792105","district":"NAMSAI","state":"ARUNACHAL PRADESH","offices":["Mahadevpur S.O (Lohit)","Podumani B.O","Kumari Kachari B.O"],"officeCount":3},{"pin":"792110","district":"DIBANG VALLEY","state":"ARUNACHAL PRADESH","offices":["Angrim Valley","Alinye","Ayeso"],"officeCount":89},{"pin":"792111","district":"LOHIT","state":"ARUNACHAL PRADESH","offices":["Yealing","20th Mile (Chailiang)","Sunpura S.O"],"officeCount":5},{"pin":"792120","district":"CHANGLANG","state":"ARUNACHAL PRADESH","offices":["Khemiyong B.O","Bubang - III","Saching - III"],"officeCount":27},{"pin":"792121","district":"CHANGLANG","state":"ARUNACHAL PRADESH","offices":["Jairampur S.O (Changlang)","Manmao B.O","Vijoynagar B.O"],"officeCount":3},{"pin":"792122","district":"CHANGLANG","state":"ARUNACHAL PRADESH","offices":["Deban B.O","Manabhum B.O","Dharampur B.O"],"officeCount":8},{"pin":"792123","district":"CHANGLANG","state":"ARUNACHAL PRADESH","offices":["Sangwal Khamlang","Tengpong","Nayang"],"officeCount":20},{"pin":"792124","district":"PAPUM PARE","state":"ARUNACHAL PRADESH","offices":["KHARSANG SO"],"officeCount":1},{"pin":"792129","district":"TIRAP","state":"ARUNACHAL PRADESH","offices":["Hukanjuri B.O","Namsang B.O","MILONPUR B.O"],"officeCount":6},{"pin":"792130","district":"TIRAP","state":"ARUNACHAL PRADESH","offices":["Kaimai B.O","Vally View B.O","Old Lainwang"],"officeCount":27},{"pin":"792131","district":"LONGDING","state":"ARUNACHAL PRADESH","offices":["Tissa B.O","Rusa","Kamku Rusa"],"officeCount":33},{"pin":"793001","district":"EAST KHASI HILLS","state":"MEGHALAYA","offices":["Shillong G.P.O.","Oakland S.O","Meghalaya Secretariat S.O"],"officeCount":3},{"pin":"793002","district":"EAST KHASI HILLS","state":"MEGHALAYA","offices":["Iewduh S.O"],"officeCount":1},{"pin":"793003","district":"EAST KHASI HILLS","state":"MEGHALAYA","offices":["Laitumkhrah S.O"],"officeCount":1},{"pin":"793004","district":"EAST KHASI HILLS","state":"MEGHALAYA","offices":["Lawsohtun B.O","Laban S.O","Rilbong S.O"],"officeCount":4},{"pin":"793005","district":"EAST KHASI HILLS","state":"MEGHALAYA","offices":["Upper Shillong S.O","Diengiei B.O","Nongumlong B.O"],"officeCount":3},{"pin":"793006","district":"EAST KHASI HILLS","state":"MEGHALAYA","offices":["Umkdait B.O","Rynjah S.O"],"officeCount":2},{"pin":"793007","district":"EAST KHASI HILLS","state":"MEGHALAYA","offices":["Happy Valley S.O"],"officeCount":1},{"pin":"793008","district":"EAST KHASI HILLS","state":"MEGHALAYA","offices":["Mawroh B.O","Phudmawri S.O"],"officeCount":2},{"pin":"793009","district":"EAST KHASI HILLS","state":"MEGHALAYA","offices":["Mawklot B.O","Mylliem Syllai U Lar B.O","Nonglyer S.O"],"officeCount":3},{"pin":"793010","district":"EAST KHASI HILLS","state":"MEGHALAYA","offices":["Laitkor B.O","Pomlakrai B.O","Laitkor Peak S.O"],"officeCount":3},{"pin":"793011","district":"EAST KHASI HILLS","state":"MEGHALAYA","offices":["Assam Rifles S.O"],"officeCount":1},{"pin":"793012","district":"EAST KHASI HILLS","state":"MEGHALAYA","offices":["Mawpat S.O","Diengpasoh B.O","Mawkhanu B.O"],"officeCount":4},{"pin":"793014","district":"EAST KHASI HILLS","state":"MEGHALAYA","offices":["Nongthymmai S.O"],"officeCount":1},{"pin":"793015","district":"EAST KHASI HILLS","state":"MEGHALAYA","offices":["Lynshing B.O","Umsawwar","Mawlang"],"officeCount":18},{"pin":"793016","district":"EAST KHASI HILLS","state":"MEGHALAYA","offices":["Mawiong S.O"],"officeCount":1},{"pin":"793017","district":"EAST KHASI HILLS","state":"MEGHALAYA","offices":["Mawlai S.O"],"officeCount":1},{"pin":"793018","district":"EAST KHASI HILLS","state":"MEGHALAYA","offices":["Neigrihms S.O"],"officeCount":1},{"pin":"793019","district":"EAST KHASI HILLS","state":"MEGHALAYA","offices":["Nongmynsong S.O"],"officeCount":1},{"pin":"793021","district":"EAST KHASI HILLS","state":"MEGHALAYA","offices":["Mawryngkneng B.O","Sohryngkham B.O","Pamora B.O"],"officeCount":7},{"pin":"793022","district":"EAST KHASI HILLS","state":"MEGHALAYA","offices":["Kynton Massar B.O","Nehu S.O","Mawtawar B.O"],"officeCount":3},{"pin":"793101","district":"RI BHOI","state":"MEGHALAYA","offices":["Killing Centre B.O","Nongrim Hills","Amjong"],"officeCount":21},{"pin":"793102","district":"RI BHOI","state":"MEGHALAYA","offices":["Lailad B.O","Umshakhon Mathon B.O","Hatumling B.O"],"officeCount":20},{"pin":"793103","district":"RI BHOI","state":"MEGHALAYA","offices":["Mawlasnai B.O","Umktieh B.O","Mawbri B.O"],"officeCount":6},{"pin":"793104","district":"RI BHOI","state":"MEGHALAYA","offices":["Mawlein Mawkhan B.O","Sumer S.O"],"officeCount":2},{"pin":"793105","district":"RI BHOI","state":"MEGHALAYA","offices":["Mawrong B.O","Mawpyrhut","Umran B.O"],"officeCount":16},{"pin":"793106","district":"EAST KHASI HILLS","state":"MEGHALAYA","offices":["Dholai B.O","Makali B.O","Mawput B.O"],"officeCount":26},{"pin":"793107","district":"EAST KHASI HILLS","state":"MEGHALAYA","offices":["Bholaganj Bazar S.O"],"officeCount":1},{"pin":"793108","district":"EAST KHASI HILLS","state":"MEGHALAYA","offices":["Laitryngew B.O","Mawblang B.O","Sohkmie B.O"],"officeCount":14},{"pin":"793109","district":"WEST JAINTIA HILLS","state":"MEGHALAYA","offices":["Naljuri B.O","Padu B.O","Sohkha B.O"],"officeCount":13},{"pin":"793110","district":"EAST KHASI HILLS","state":"MEGHALAYA","offices":["Pamshutia B.O","Mawbeh B.O","Wahshiarkhmut B.O"],"officeCount":20},{"pin":"793111","district":"EAST KHASI HILLS","state":"MEGHALAYA","offices":["Ladmawphlang B.O"],"officeCount":1},{"pin":"793112","district":"EAST KHASI HILLS","state":"MEGHALAYA","offices":["Nongriat","Shella S.O","Mawlong B.O"],"officeCount":7},{"pin":"793113","district":"EAST KHASI HILLS","state":"MEGHALAYA","offices":["Phlangwanbroi B.O","Syntein B.O","Tynger B.O"],"officeCount":11},{"pin":"793114","district":"SOUTH WEST KHASI HILLS","state":"MEGHALAYA","offices":["Laitnongrim B.O","Mawlyngwir B.O","Phudjaud B.O"],"officeCount":25},{"pin":"793115","district":"EAST KHASI HILLS","state":"MEGHALAYA","offices":["Sohiong S.O","Krang B.O"],"officeCount":2},{"pin":"793116","district":"RI BHOI","state":"MEGHALAYA","offices":["Sohliya Iapngar","Raitong","Bhoilymbong S.O"],"officeCount":4},{"pin":"793119","district":"SOUTH WEST KHASI HILLS","state":"MEGHALAYA","offices":["Kyrdum","Byrki B.O","Langdongdai B.O"],"officeCount":75},{"pin":"793120","district":"EAST KHASI HILLS","state":"MEGHALAYA","offices":["Khlieh Lyngkhoi B.O","Laitdombah B.O","Manai B.O"],"officeCount":34},{"pin":"793121","district":"EAST KHASI HILLS","state":"MEGHALAYA","offices":["Mawpun B.O","Nongspung B.O","Weiloi B.O"],"officeCount":15},{"pin":"793122","district":"RI BHOI","state":"MEGHALAYA","offices":["Ucc S.O"],"officeCount":1},{"pin":"793123","district":"RI BHOI","state":"MEGHALAYA","offices":["Umsaw S.O"],"officeCount":1},{"pin":"793126","district":"WEST KHASI HILLS","state":"MEGHALAYA","offices":["Nongma","Nongpdeng","Agreng"],"officeCount":43},{"pin":"793150","district":"WEST JAINTIA HILLS","state":"MEGHALAYA","offices":["Iawthymmai B.O","Jarain B.O","Kyndong Tuber B.O"],"officeCount":31},{"pin":"793151","district":"WEST JAINTIA HILLS","state":"MEGHALAYA","offices":["Nartiang B.O","Laru","Sanaroo"],"officeCount":20},{"pin":"793160","district":"EAST JAINTIA HILLS","state":"MEGHALAYA","offices":["Rymbai B.O","Sham Sham B.O","Tuber Kmaishnong B.O"],"officeCount":11},{"pin":"793161","district":"WEST JAINTIA HILLS","state":"MEGHALAYA","offices":["Amlarem S.O","Amlari B.O"],"officeCount":2},{"pin":"793200","district":"EAST JAINTIA HILLS","state":"MEGHALAYA","offices":["Sutnga B.O","Umkiang B.O","Sakwa"],"officeCount":31},{"pin":"793210","district":"EAST JAINTIA HILLS","state":"MEGHALAYA","offices":["Rata Cherra B.O","Sheruphie B.O","Hingaria"],"officeCount":7},{"pin":"794001","district":"WEST GARO HILLS","state":"MEGHALAYA","offices":["Tura H.O"],"officeCount":1},{"pin":"794002","district":"WEST GARO HILLS","state":"MEGHALAYA","offices":["Dajongpara B.O","Gabil B.O","Rongkhon B.O"],"officeCount":31},{"pin":"794003","district":"WEST GARO HILLS","state":"MEGHALAYA","offices":["Durigre","Dabigre","Amingokgre"],"officeCount":10},{"pin":"794004","district":"WEST GARO HILLS","state":"MEGHALAYA","offices":["Rimrang Bonegre","Chinabat","Mandagre"],"officeCount":10},{"pin":"794005","district":"WEST GARO HILLS","state":"MEGHALAYA","offices":["Jebalgiri","Naronggre","Dana Adugiri"],"officeCount":28},{"pin":"794101","district":"WEST GARO HILLS","state":"MEGHALAYA","offices":["Araimile S.O","Gambarigre","Captain Reserve B.O"],"officeCount":4},{"pin":"794102","district":"SOUTH GARO HILLS","state":"MEGHALAYA","offices":["Balkhalbazar B.O","Mendikgiri B.O","Chibagre"],"officeCount":71},{"pin":"794103","district":"WEST GARO HILLS","state":"MEGHALAYA","offices":["Chandabhui B.O","Chengapara B.O","Dimapara B.O"],"officeCount":20},{"pin":"794104","district":"WEST GARO HILLS","state":"MEGHALAYA","offices":["Mechanpani B.O","Bikonggre B.O","Cheran Songmagre"],"officeCount":23},{"pin":"794105","district":"WEST GARO HILLS","state":"MEGHALAYA","offices":["Okkapara B.O","Teporpara B.O","Zekabari B.O"],"officeCount":17},{"pin":"794106","district":"SOUTH WEST GARO HILLS","state":"MEGHALAYA","offices":["Chapahati B.O","Majerchar B.O","Kalaipara B.O"],"officeCount":8},{"pin":"794107","district":"SOUTH GARO HILLS","state":"MEGHALAYA","offices":["Jadigitim B.O","Shinianggri","Riangshi A"],"officeCount":5},{"pin":"794108","district":"NORTH GARO HILLS","state":"MEGHALAYA","offices":["Thapa B.O","Eguagre","Dilma Songgital"],"officeCount":28},{"pin":"794109","district":"WEST GARO HILLS","state":"MEGHALAYA","offices":["Kentapara","Dotronggre","Dabanggre"],"officeCount":24},{"pin":"794110","district":"EAST GARO HILLS","state":"MEGHALAYA","offices":["Dabu B.O","Dainadubi B.O","Ronga Agal B.O"],"officeCount":26},{"pin":"794111","district":"EAST GARO HILLS","state":"MEGHALAYA","offices":["Samanda B.O","Songsak B.O","Rongap Mikilsim"],"officeCount":40},{"pin":"794112","district":"WEST GARO HILLS","state":"MEGHALAYA","offices":["Rangga","Dochisoram","Rangsa"],"officeCount":17},{"pin":"794113","district":"EAST GARO HILLS","state":"MEGHALAYA","offices":["Gairong B.O","Gambil B.O","Chikal Dawa"],"officeCount":8},{"pin":"794114","district":"SOUTH GARO HILLS","state":"MEGHALAYA","offices":["Mohadeo Warima","Warimagiri B.O","Teptepa"],"officeCount":11},{"pin":"794115","district":"SOUTH WEST GARO HILLS","state":"MEGHALAYA","offices":["Kalaichar B.O","Salmanpara B.O","Zigzak B.O"],"officeCount":21},{"pin":"794116","district":"NA","state":"NA","offices":["HALLIDAYGANJ SO"],"officeCount":1},{"pin":"795001","district":"IMPHAL WEST","state":"MANIPUR","offices":["Imphal H.O","D.M College S.O","Imphal Bazar S.O"],"officeCount":4},{"pin":"795002","district":"KANGPOKPI","state":"MANIPUR","offices":["Karakhul B.O","Khurukhul B.O","Luwangsangbam B.O"],"officeCount":11},{"pin":"795003","district":"IMPHAL WEST","state":"MANIPUR","offices":["Kunja (P) B.O","Kyamgei B.O","Mongsangei B.O"],"officeCount":7},{"pin":"795004","district":"IMPHAL WEST","state":"MANIPUR","offices":["Central Agriculture University B.O","Lamboi Khongnagkhong B.O","Sayang Kuraomakhong B.O"],"officeCount":9},{"pin":"795005","district":"IMPHAL EAST","state":"MANIPUR","offices":["Moirang Kampu B.O","Kshetribangoon B.O","Awang Kongpal B.O"],"officeCount":7},{"pin":"795006","district":"PHERZAWL","state":"MANIPUR","offices":["Bungmual B.O","Lingshiphai B.O","Mission Compound B.O"],"officeCount":25},{"pin":"795007","district":"SENAPATI","state":"MANIPUR","offices":["Thingba Khullen B.O","Thingba Khunou B.O","Willong B.O"],"officeCount":8},{"pin":"795008","district":"IMPHAL WEST","state":"MANIPUR","offices":["Khongnangpheidekpi B.O","Mongkhang Lambi B.O","Irilbung B.O"],"officeCount":12},{"pin":"795009","district":"IMPHAL WEST","state":"MANIPUR","offices":["Bitrarakhong B.O","Samurou B.O","Haoreibi B.O"],"officeCount":10},{"pin":"795010","district":"KANGPOKPI","state":"MANIPUR","offices":["Moirang Purel B.O","Ningthemchakhul B.O","Nongdam Tangkhul B.O"],"officeCount":16},{"pin":"795011","district":"BISHNUPUR","state":"MANIPUR","offices":["Potsangbam B.O","Ningthoukhong SO","Haotak Khullen B.O"],"officeCount":6},{"pin":"795015","district":"SENAPATI","state":"MANIPUR","offices":["Koide B.O","Purul B.O","Lakhamei B.O"],"officeCount":6},{"pin":"795101","district":"KAKCHING","state":"MANIPUR","offices":["Chairen B.O","Jul Bangching B.O","K. Molnom B.O"],"officeCount":16},{"pin":"795102","district":"CHANDEL","state":"MANIPUR","offices":["Monbi B.O","Phiran Machet B.O","Thorchom B.O"],"officeCount":32},{"pin":"795103","district":"THOUBAL","state":"MANIPUR","offices":["Kalikalok B.O","Naodam Bazar B.O","Arong Nongmaikhong B.O"],"officeCount":21},{"pin":"795104","district":"SENAPATI","state":"MANIPUR","offices":["Chingai Khullen B.O","Saranamei B.O","Tungjoy B.O"],"officeCount":12},{"pin":"795105","district":"SENAPATI","state":"MANIPUR","offices":["Ngari Khullen B.O","Maram S.O"],"officeCount":2},{"pin":"795106","district":"KANGPOKPI","state":"MANIPUR","offices":["Tumuyan Khullen B.O","Senapati S.O","Oklong B.O"],"officeCount":4},{"pin":"795107","district":"KANGPOKPI","state":"MANIPUR","offices":["S.Bolkot B.O","Thingsat B.O","Nurathel B.O"],"officeCount":8},{"pin":"795112","district":"KANGPOKPI","state":"MANIPUR","offices":["Chalwa (P) B.O","Cheljang B.O","Irang B.O"],"officeCount":7},{"pin":"795113","district":"IMPHAL WEST","state":"MANIPUR","offices":["New Keithelmanbi B.O","Ngairangbam B.O","Tairenpokpi B.O"],"officeCount":18},{"pin":"795114","district":"IMPHAL EAST","state":"MANIPUR","offices":["Pngaei Yangdong S.O","Haraorou B.O","Kairang Litan Makhong B.O"],"officeCount":16},{"pin":"795115","district":"JIRIBAM","state":"MANIPUR","offices":["BR Colony B.O","Gularthol S.O","New Keiphundai B.O"],"officeCount":7},{"pin":"795116","district":"JIRIBAM","state":"MANIPUR","offices":["Bongmun B.O","Borobekra B.O","Champanagar B.O"],"officeCount":18},{"pin":"795117","district":"CHURACHANDPUR","state":"MANIPUR","offices":["Khouwpuibung B.O","Mual Vaiphei B.O","Tuitengphai B.O"],"officeCount":7},{"pin":"795118","district":"KANGPOKPI","state":"MANIPUR","offices":["Jangnoi B.O","Molkon B.O","Tingpibung B.O"],"officeCount":16},{"pin":"795121","district":"IMPHAL WEST","state":"MANIPUR","offices":["PARBUNG SO"],"officeCount":1},{"pin":"795122","district":"KANGPOKPI","state":"MANIPUR","offices":["Tokpa B.O","Keithelmanbi B.O","Kheljang B.O"],"officeCount":8},{"pin":"795124","district":"CHURACHANDPUR","state":"MANIPUR","offices":["Mayuran B.O","Loktak Project S.O","Leimatak B.O"],"officeCount":7},{"pin":"795125","district":"TAMENGLONG","state":"MANIPUR","offices":["Lemta B.O","Tamei S.O","Illeng B.O"],"officeCount":13},{"pin":"795126","district":"KANGPOKPI","state":"MANIPUR","offices":["Khoijuman B.O","Toubul B.O","Bishnupur S.O (Bishnupur)"],"officeCount":14},{"pin":"795127","district":"CHANDEL","state":"MANIPUR","offices":["Duthang B.O","Larong B.O","Mittong B.O"],"officeCount":11},{"pin":"795128","district":"CHURACHANDPUR","state":"MANIPUR","offices":["Henglep B.O","Munpi B.O","Saikhul Village B.O"],"officeCount":38},{"pin":"795129","district":"KANGPOKPI","state":"MANIPUR","offices":["Kangpokpi Mission B.O","Toribari B.O","Kangpokpi S.O"],"officeCount":7},{"pin":"795130","district":"IMPHAL EAST","state":"MANIPUR","offices":["Urup B.O","Chajing Pt II B.O","Lairabokhong B.O"],"officeCount":11},{"pin":"795131","district":"TENGNOUPAL","state":"MANIPUR","offices":["Tengnoupal B.O","Choktong","Moreh S.O"],"officeCount":16},{"pin":"795132","district":"KAKCHING","state":"MANIPUR","offices":["Arong B.O","Irong Chessabal B.O","Sekmaijin B.O"],"officeCount":24},{"pin":"795133","district":"BISHNUPUR","state":"MANIPUR","offices":["Boroyangbi B.O","Bunglon B.O","Kumbi (P) B.O"],"officeCount":30},{"pin":"795134","district":"IMPHAL WEST","state":"MANIPUR","offices":["Awangjiri B.O","Thingkai Khullen B.O","Irengbam B.O"],"officeCount":21},{"pin":"795135","district":"CHANDEL","state":"MANIPUR","offices":["Angbrashu B.O","Liwachangning B.O","Narum B.O"],"officeCount":27},{"pin":"795136","district":"IMPHAL WEST","state":"MANIPUR","offices":["Kanglatongbi B.O","Awang Leikinthabi B.O","Luwangsangol B.O"],"officeCount":7},{"pin":"795138","district":"THOUBAL","state":"MANIPUR","offices":["Charangpat B.O","Khangabok B.O","Phoudel B.O"],"officeCount":21},{"pin":"795139","district":"CHURACHANDPUR","state":"MANIPUR","offices":["Sialbu B.O","Suangdoh B.O","Vokbual B.O"],"officeCount":13},{"pin":"795140","district":"IMPHAL WEST","state":"MANIPUR","offices":["Laiphrakom B.O","Sangaiprou B.O","Yarrow Meitram B.O"],"officeCount":4},{"pin":"795141","district":"TAMENGLONG","state":"MANIPUR","offices":["Kahulong B.O","Longpram B.O","Tamenglong Khunjao B.O"],"officeCount":25},{"pin":"795142","district":"UKHRUL","state":"MANIPUR","offices":["Hundung B.O","Siroi B.O","Tolloi B.O"],"officeCount":37},{"pin":"795143","district":"PHERZAWL","state":"MANIPUR","offices":["Pamjal B.O","Hanship B.O","Tualbung B.O"],"officeCount":4},{"pin":"795144","district":"UKHRUL","state":"MANIPUR","offices":["Kachai B.O","Khongdei Simphung B.O","Phadang B.O"],"officeCount":6},{"pin":"795145","district":"KAMJONG","state":"MANIPUR","offices":["Ashi B.O","Chassad B.O","Grihang B.O"],"officeCount":52},{"pin":"795146","district":"IMPHAL WEST","state":"MANIPUR","offices":["Mayang Langjing B.O","Lamsang S.O","Ijairong B.O"],"officeCount":16},{"pin":"795147","district":"NONEY","state":"MANIPUR","offices":["Sekjang","Kambiron B.O","Rengpang B.O"],"officeCount":12},{"pin":"795148","district":"THOUBAL","state":"MANIPUR","offices":["Salungpham B.O","Khongjom B.O","Phundrei B.O"],"officeCount":15},{"pin":"795149","district":"KANGPOKPI","state":"MANIPUR","offices":["Changamdabi B.O","Kamuching B.O","Phouoibi B.O"],"officeCount":27},{"pin":"795150","district":"SENAPATI","state":"MANIPUR","offices":["Mao S.O","Pudunamei B.O","Pfukhro B.O"],"officeCount":4},{"pin":"795159","district":"NONEY","state":"MANIPUR","offices":["Awangkhul B.O","Nagaching B.O","New Kabui Khullen B.O"],"officeCount":10},{"pin":"795160","district":"NA","state":"NA","offices":["Tousem SO"],"officeCount":1},{"pin":"796001","district":"AIZAWL","state":"MIZORAM","offices":["Aizawl H.O"],"officeCount":1},{"pin":"796004","district":"AIZAWL","state":"MIZORAM","offices":["Mizoram University S.O"],"officeCount":1},{"pin":"796005","district":"AIZAWL","state":"MIZORAM","offices":["Thingdawlmelriat B.O","ZORAM MEDICAL COLLEGE BO","Missionvengthlang B.O"],"officeCount":16},{"pin":"796006","district":"AIZAWL","state":"MIZORAM","offices":["NEW SECRETARIAT"],"officeCount":1},{"pin":"796007","district":"AIZAWL","state":"MIZORAM","offices":["Edenthar B.O","Bethlehem B.O","Ramthar B.O"],"officeCount":5},{"pin":"796008","district":"AIZAWL","state":"MIZORAM","offices":["Armed Veng S.O"],"officeCount":1},{"pin":"796009","district":"AIZAWL","state":"MIZORAM","offices":["Chawlhhmun B.O","Govt. Complex B.O","Luangmual B.O"],"officeCount":8},{"pin":"796012","district":"AIZAWL","state":"MIZORAM","offices":["Ramhlun S.O"],"officeCount":1},{"pin":"796014","district":"AIZAWL","state":"MIZORAM","offices":["Bawngkawn S.O"],"officeCount":1},{"pin":"796015","district":"AIZAWL","state":"MIZORAM","offices":["Muthi B.O","Selesih B.O","Lungdai B.O"],"officeCount":6},{"pin":"796017","district":"AIZAWL","state":"MIZORAM","offices":["Khawruhlian B.O","Sawleng B.O","Phaileng E B.O"],"officeCount":10},{"pin":"796070","district":"KOLASIB","state":"MIZORAM","offices":["Mualvum B.O","Kawnpui S.O","Bukpui B.O"],"officeCount":11},{"pin":"796081","district":"KOLASIB","state":"MIZORAM","offices":["Thingdawl B.O","Bairabi B.O","Suarhliap B.O"],"officeCount":12},{"pin":"796091","district":"KOLASIB","state":"MIZORAM","offices":["Phaisen B.O","Tuirial H.E.P B.O","N.Chawnpui B.O"],"officeCount":6},{"pin":"796101","district":"KOLASIB","state":"MIZORAM","offices":["Saiphai B.O","Phainuam B.O","Vairengte S.O"],"officeCount":3},{"pin":"796111","district":"AIZAWL","state":"MIZORAM","offices":["Khawpuar B.O","N.Tinghmun B.O","Sakawrdai B.O"],"officeCount":16},{"pin":"796161","district":"SERCHHIP","state":"MIZORAM","offices":["Hmuntha B.O","Khumtung B.O","Seling B.O"],"officeCount":10},{"pin":"796181","district":"SERCHHIP","state":"MIZORAM","offices":["Keitum B.O","Lungpho B.O","Thinglian B.O"],"officeCount":12},{"pin":"796184","district":"SERCHHIP","state":"MIZORAM","offices":["N. Vanlaiphai S.O","Chekawn B.O","Lungchhuan B.O"],"officeCount":5},{"pin":"796186","district":"SERCHHIP","state":"MIZORAM","offices":["Kanghmun S B.O","BUANGPUI","Ramlaitui B.O"],"officeCount":7},{"pin":"796190","district":"AIZAWL","state":"MIZORAM","offices":["Maubuang B.O","Phulpui B.O","Sailam B.O"],"officeCount":12},{"pin":"796246","district":"AIZAWL","state":"MIZORAM","offices":["LUNGSEL"],"officeCount":1},{"pin":"796261","district":"SAITUAL","state":"MIZORAM","offices":["Changzawl B.O","N.E.Bualpui B.O","N.Khawlek B.O"],"officeCount":23},{"pin":"796290","district":"SAITUAL","state":"MIZORAM","offices":["Ne Khawdungsei B.O","Kawlbem B.O","Ngopa S.O"],"officeCount":6},{"pin":"796291","district":"SAITUAL","state":"MIZORAM","offices":["Hrianghmun B.O","Teikhang B.O","MIMBUNG S.O"],"officeCount":4},{"pin":"796310","district":"KHAWZAWL","state":"MIZORAM","offices":["Chawngtlai B.O","Khawzawl S.O","Chhawrtui B.O"],"officeCount":19},{"pin":"796320","district":"CHAMPHAI","state":"MIZORAM","offices":["Dungtlang B.O","THEKTE","THEKPUI"],"officeCount":16},{"pin":"796321","district":"CHAMPHAI","state":"MIZORAM","offices":["Bethel B.O","Ngur B.O","Ruantlang B.O"],"officeCount":26},{"pin":"796370","district":"SERCHHIP","state":"MIZORAM","offices":["Lungdar S.O","Tlangpui B.O","Leng B.O"],"officeCount":7},{"pin":"796410","district":"KOLASIB","state":"MIZORAM","offices":["Mualkhang B.O","Rawpuichhip B.O","SIHHMUI"],"officeCount":6},{"pin":"796421","district":"MAMIT","state":"MIZORAM","offices":["Hmunpui B.O","Lengpui Airport S.O"],"officeCount":2},{"pin":"796431","district":"MAMIT","state":"MIZORAM","offices":["Phuldungsei B.O","Silsury B.O","Tuipuibari B.O"],"officeCount":15},{"pin":"796441","district":"AIZAWL","state":"MIZORAM","offices":["Kawrtethawveng B.O","N.Sabual B.O","LUANGPAWL"],"officeCount":12},{"pin":"796470","district":"AIZAWL","state":"MIZORAM","offices":["Boraibazar B.O","Momcherra B.O","Zawlnuam BO"],"officeCount":9},{"pin":"796501","district":"MAMIT","state":"MIZORAM","offices":["Darlung B.O","Rulpuihlim B.O","S.Sabual B.O"],"officeCount":9},{"pin":"796571","district":"Hnahthial","state":"MIZORAM","offices":["Darzo B.O","LUNGMAWI","Chawngtui B.O"],"officeCount":16},{"pin":"796691","district":"LUNGLEI","state":"MIZORAM","offices":["Pukpui B.O","Ralvawng B.O","Zohnuai B.O"],"officeCount":7},{"pin":"796701","district":"LUNGLEI","state":"MIZORAM","offices":["Sesawm B.O","Buarpui B.O","Hauruang B.O"],"officeCount":37},{"pin":"796710","district":"LUNGLEI","state":"MIZORAM","offices":["Laisawral B.O"],"officeCount":1},{"pin":"796751","district":"LUNGLEI","state":"MIZORAM","offices":["S.Chawilung B.O","Zodin B.O","SUMASUMI"],"officeCount":12},{"pin":"796770","district":"AIZAWL","state":"MIZORAM","offices":["Jarulsury B.O","Sumsilui B.O","Udaisury B.O"],"officeCount":13},{"pin":"796891","district":"LAWNGTLAI","state":"MIZORAM","offices":["Balhlakawn B.O","Kawlchaw W B.O","Paithar B.O"],"officeCount":32},{"pin":"796901","district":"LAWNGTLAI","state":"MIZORAM","offices":["Tuipuiferry B.O","Lungtian B.O","Pangkhua B.O"],"officeCount":39},{"pin":"797001","district":"KOHIMA","state":"NAGALAND","offices":["Kohima H.O"],"officeCount":1},{"pin":"797002","district":"KOHIMA","state":"NAGALAND","offices":["Khonoma B.O","Poilwa B.O","Kohima Science College S.O"],"officeCount":5},{"pin":"797003","district":"KOHIMA","state":"NAGALAND","offices":["Chakhabama B.O","Kizocha B.O","Ciesema B.O"],"officeCount":8},{"pin":"797004","district":"KOHIMA","state":"NAGALAND","offices":["Meriema B.O","Thizama B.O","New Sectt Complex S.O"],"officeCount":3},{"pin":"797006","district":"KOHIMA","state":"NAGALAND","offices":["Kigwema B.O","Viswema B.O","Kedima B.O"],"officeCount":6},{"pin":"797099","district":"WOKHA","state":"NAGALAND","offices":["Liowokha Old","Wozhu Old","Bhandari S.O"],"officeCount":3},{"pin":"797101","district":"PEREN","state":"NAGALAND","offices":["N.Song B.O","Tening B.O","Nchongram B.O"],"officeCount":5},{"pin":"797103","district":"DIMAPUR","state":"NAGALAND","offices":["Nihekhu B.O","Pimla B.O","Tenyiphe B.O"],"officeCount":7},{"pin":"797104","district":"PHEK","state":"NAGALAND","offices":["Phugwu B.O","Dzulhami B.O","Yorubami B.O"],"officeCount":10},{"pin":"797105","district":"KOHIMA","state":"NAGALAND","offices":["Phekerkriema","Zhadima B.O","Botsa B.O"],"officeCount":8},{"pin":"797106","district":"DIMAPUR","state":"NAGALAND","offices":["Jharnapani B.O","Molvom B.O","Punglwa B.O"],"officeCount":11},{"pin":"797107","district":"PHEK","state":"NAGALAND","offices":["Kikruma B.O","Sakraba B.O","Zavame B.O"],"officeCount":15},{"pin":"797108","district":"PHEK","state":"NAGALAND","offices":["Losami B.O","Ketsapo B.O","Luzaphuhu B.O"],"officeCount":7},{"pin":"797109","district":"ZUNHEBOTO","state":"NAGALAND","offices":["Ghathashi B.O","Zephenyu B.O","Lazami B.O"],"officeCount":15},{"pin":"797110","district":"PEREN","state":"NAGALAND","offices":["Khelma B.O","Saijang","Athibung B.O"],"officeCount":13},{"pin":"797111","district":"WOKHA","state":"NAGALAND","offices":["Sungro B.O","Elumnyu B.O","Nyiro B.O"],"officeCount":23},{"pin":"797112","district":"PEREN","state":"NAGALAND","offices":["Hening Kunglwa B.O","Khermahal B.O","Hakhizhe B.O"],"officeCount":13},{"pin":"797113","district":"DIMAPUR","state":"NAGALAND","offices":["D. C. Complex B.O","Duncan Basti B.O","Kacharigaon"],"officeCount":6},{"pin":"797114","district":"PHEK","state":"NAGALAND","offices":["Akhegwo B.O","Pungkhuri B.O","Reguri"],"officeCount":8},{"pin":"797115","district":"DIMAPUR","state":"NAGALAND","offices":["Aoyimti B.O","Sukhovi B.O","Diphupar B.O"],"officeCount":10},{"pin":"797116","district":"DIMAPUR","state":"NAGALAND","offices":["Khehekhu B.O","Padampukhuri B.O","Dimapur Bazar S.O"],"officeCount":6},{"pin":"797117","district":"DIMAPUR","state":"NAGALAND","offices":["Circular Road S.O","Pwd Colony B.O","Zeliangrong B.O"],"officeCount":3},{"pin":"797118","district":"DIMAPUR","state":"NAGALAND","offices":["Signal Village","Thahekhu B.O","Rangapahar B.O"],"officeCount":3},{"pin":"797120","district":"KOHIMA","state":"NAGALAND","offices":["Zubza B.O","Pfuchama","P.R Hill S.O"],"officeCount":5},{"pin":"797121","district":"KOHIMA","state":"NAGALAND","offices":["Monkhola S.O"],"officeCount":1},{"pin":"798601","district":"TUENSANG","state":"NAGALAND","offices":["Chare B.O","Fazl Ali College B.O","Longmisa B.O"],"officeCount":16},{"pin":"798602","district":"MON","state":"NAGALAND","offices":["Tiru Upper","Oting","Namsa B.O"],"officeCount":7},{"pin":"798603","district":"MON","state":"NAGALAND","offices":["Chengloisho B.O","Chinglong B.O","Pessao B.O"],"officeCount":12},{"pin":"798604","district":"MOKOKCHUNG","state":"NAGALAND","offices":["Khari B.O","Longchem B.O","Aonokpu"],"officeCount":12},{"pin":"798607","district":"MOKOKCHUNG","state":"NAGALAND","offices":["Longkhum B.O","Mangmentong B.O","Arree Old B.O"],"officeCount":4},{"pin":"798611","district":"KIPHIRE","state":"NAGALAND","offices":["Kisethong B.O","Pungro B.O","Singrup B.O"],"officeCount":21},{"pin":"798612","district":"TUENSANG","state":"NAGALAND","offices":["Kongsang B.O","Choklangan B.O","Sanglao B.O"],"officeCount":33},{"pin":"798613","district":"MOKOKCHUNG","state":"NAGALAND","offices":["Chantongia S.O","Yaongyimsen B.O"],"officeCount":2},{"pin":"798614","district":"MOKOKCHUNG","state":"NAGALAND","offices":["Mongsenyimti B.O","Chuchuyimlang S.O","Salulamang B.O"],"officeCount":7},{"pin":"798615","district":"MOKOKCHUNG","state":"NAGALAND","offices":["Kubulong B.O","Impur S.O","Longjang B.O"],"officeCount":4},{"pin":"798616","district":"TUENSANG","state":"NAGALAND","offices":["Yangli B.O","Chungtore B.O","Longkhim S.O"],"officeCount":5},{"pin":"798617","district":"KOHIMA","state":"NAGALAND","offices":["Pungro"],"officeCount":1},{"pin":"798618","district":"MOKOKCHUNG","state":"NAGALAND","offices":["Luyang Valley B.O","Tamlu B.O","Merangkong B.O"],"officeCount":9},{"pin":"798620","district":"ZUNHEBOTO","state":"NAGALAND","offices":["Aghunato B.O","Asukhomi B.O","Asuto B.O"],"officeCount":33},{"pin":"798621","district":"MON","state":"NAGALAND","offices":["Longpong Senghe B.O","Longwa B.O","Singha Chingnyu B.O"],"officeCount":10},{"pin":"798622","district":"MON","state":"NAGALAND","offices":["Baranamsang B.O","Kongon B.O","Naginimora S.O"],"officeCount":3},{"pin":"798623","district":"MOKOKCHUNG","state":"NAGALAND","offices":["Paper Nagar S.O","Anaki","Yajang C"],"officeCount":3},{"pin":"798625","district":"LONGLENG","state":"NAGALAND","offices":["Longleng S.O","Yachem B.O","Yongyak B.O"],"officeCount":11},{"pin":"798626","district":"KOHIMA","state":"NAGALAND","offices":["Noklak SO"],"officeCount":1},{"pin":"798627","district":"ZUNHEBOTO","state":"NAGALAND","offices":["Aizuto B.O","Lumami S.O","Akuluto B.O"],"officeCount":3},{"pin":"798628","district":"TUENSANG","state":"NAGALAND","offices":["Huker B.O","Kuthur B.O","Shampur B.O"],"officeCount":11},{"pin":"799001","district":"Nirmal","state":"TELANGANA","offices":["Jaganath Bari Road S.O","Agartala H.O","Agartala Bazar S.O"],"officeCount":5},{"pin":"799002","district":"West Tripura","state":"TRIPURA","offices":["AgartalaGuard Post B.O","Border Rampur B.O","Town Rampur B.O"],"officeCount":7},{"pin":"799003","district":"West Tripura","state":"TRIPURA","offices":["Ishanchandranagar B.O","Madhuban B.O","S.D.Mission Colony B.O"],"officeCount":9},{"pin":"799004","district":"West Tripura","state":"TRIPURA","offices":["Aralia B.O","Jogendranagar B.O","Nagicherra B.O"],"officeCount":12},{"pin":"799005","district":"West Tripura","state":"TRIPURA","offices":["Abhoynagar S.O"],"officeCount":1},{"pin":"799006","district":"West Tripura","state":"TRIPURA","offices":["Bankumari E/SB B.O","Nandannagar B.O","Kunjaban S.O"],"officeCount":8},{"pin":"799007","district":"West Tripura","state":"TRIPURA","offices":["Banamalipur B.O","Dhaleswar S.O"],"officeCount":2},{"pin":"799008","district":"West Tripura","state":"TRIPURA","offices":["Khasnoagaon B.O","Mariamnagar B.O","Neepco B.O"],"officeCount":9},{"pin":"799009","district":"West Tripura","state":"TRIPURA","offices":["Lankamura B.O","Durjaynagar B.O","Narayanpur B.O"],"officeCount":5},{"pin":"799010","district":"West Tripura","state":"TRIPURA","offices":["Agartala Secretariat S.O"],"officeCount":1},{"pin":"799011","district":"Sepahijala","state":"TRIPURA","offices":["Jampuijala Colony B.O","Kendraicherra B.O","Sankumabari B.O"],"officeCount":7},{"pin":"799012","district":"NA","state":"NA","offices":["Durgabari","Salbagan S.O","Gandhigram B.O"],"officeCount":3},{"pin":"799013","district":"Gomati","state":"TRIPURA","offices":["Dakshin Maharani B.O","Holakhet B.O","Maharani B.O"],"officeCount":11},{"pin":"799014","district":"West Tripura","state":"TRIPURA","offices":["Agartala ONGC S.O"],"officeCount":1},{"pin":"799015","district":"West Tripura","state":"TRIPURA","offices":["Tebaria B.O","Narayanpur Bazar SO"],"officeCount":2},{"pin":"799022","district":"West Tripura","state":"TRIPURA","offices":["Tripura University S.O"],"officeCount":1},{"pin":"799035","district":"West Tripura","state":"TRIPURA","offices":["Burakha Landless Colony B.O","Dinabandhupara B.O","Meghlipara B.O"],"officeCount":9},{"pin":"799045","district":"West Tripura","state":"TRIPURA","offices":["Champaknagar B.O","Noabadi B.O","Gurudas Colony B.O"],"officeCount":14},{"pin":"799046","district":"West Tripura","state":"TRIPURA","offices":["NIT Agartala S.O"],"officeCount":1},{"pin":"799101","district":"Gomati","state":"TRIPURA","offices":["Gamakubari B.O","Kurma B.O","Nagrai B.O"],"officeCount":19},{"pin":"799102","district":"Sepahijala","state":"TRIPURA","offices":["Kalkalia B.O","Lalsingmura B.O","Nabinagar B.O"],"officeCount":30},{"pin":"799103","district":"Sepahijala","state":"TRIPURA","offices":["Charilam B.O","Latiacherra B.O","South Charilam B.O"],"officeCount":15},{"pin":"799104","district":"Gomati","state":"TRIPURA","offices":["Karbook B.O","Purba Manikya Dewan B.O","Ghorakappa B.O"],"officeCount":16},{"pin":"799105","district":"Gomati","state":"TRIPURA","offices":["Dhuptali B.O","Hadra B.O","Kusumara B.O"],"officeCount":20},{"pin":"799113","district":"Gomati","state":"TRIPURA","offices":["Bagma B.O","East Bagabassa B.O","Tepania S.O"],"officeCount":5},{"pin":"799114","district":"Gomati","state":"TRIPURA","offices":["Raiyabari B.O","Pitra Bazar B.O","Rajarbag B.O"],"officeCount":11},{"pin":"799115","district":"Sepahijala","state":"TRIPURA","offices":["Bagabassa B.O","Jumerdhepa B.O","Kemtali B.O"],"officeCount":16},{"pin":"799120","district":"Gomati","state":"TRIPURA","offices":["Radhakishorepur H.O","IDC Radhakishorepur HO"],"officeCount":2},{"pin":"799125","district":"Gomati","state":"TRIPURA","offices":["Gangacherra B.O","Paikhola B.O","Rajapur B.O"],"officeCount":8},{"pin":"799130","district":"West Tripura","state":"TRIPURA","offices":["Kanchanmala B.O","Pandavpur B.O","Pravapur B.O"],"officeCount":9},{"pin":"799131","district":"Sepahijala","state":"TRIPURA","offices":["Durgapur B.O","Khedabari B.O","Kamalnagar B.O"],"officeCount":12},{"pin":"799132","district":"Sepahijala","state":"TRIPURA","offices":["Maheshpur B.O","Bhabanipur B.O","Kalikrishnagar B.O"],"officeCount":7},{"pin":"799141","district":"South Tripura","state":"TRIPURA","offices":["Debdaru Bazar B.O","Thakurcherra B.O","Jolaibari S.O"],"officeCount":9},{"pin":"799142","district":"South Tripura","state":"TRIPURA","offices":["Muhuri Ratanpur B.O","Charakbai B.O","Muhuripur S.O"],"officeCount":3},{"pin":"799143","district":"South Tripura","state":"TRIPURA","offices":["Bhuratali B.O","Bishnupur B.O","Poangbari B.O"],"officeCount":12},{"pin":"799144","district":"South Tripura","state":"TRIPURA","offices":["Bagafa B.O","Baikhora B.O","Urrat Takmacherra B.O"],"officeCount":14},{"pin":"799145","district":"South Tripura","state":"TRIPURA","offices":["Chalitacherra B.O","Sabroom S.O","Baishnabpur B.O"],"officeCount":13},{"pin":"799150","district":"South Tripura","state":"TRIPURA","offices":["Rajnagar S.O (South Tripura)","Kasari B.O"],"officeCount":2},{"pin":"799153","district":"South Tripura","state":"TRIPURA","offices":["Radhanagar S.O (West Tripura)","Rangamura B.O"],"officeCount":2},{"pin":"799155","district":"South Tripura","state":"TRIPURA","offices":["Abhoyganj Bazar B.O","Paschim Pipariakhola B.O","Dakshin Sonaicharri B.O"],"officeCount":15},{"pin":"799156","district":"South Tripura","state":"TRIPURA","offices":["Nalua B.O","South Krishnagar B.O","Hrishyamukh S.O"],"officeCount":5},{"pin":"799157","district":"South Tripura","state":"TRIPURA","offices":["Puran Rajbari B.O","Siddhinagar B.O","Gouranga Bazar B.O"],"officeCount":8},{"pin":"799201","district":"Khowai","state":"TRIPURA","offices":["Behalabari B.O","Ganki B.O","Samatal Padmabil B.O"],"officeCount":20},{"pin":"799202","district":"Khowai","state":"TRIPURA","offices":["Khowai Court S.O"],"officeCount":1},{"pin":"799203","district":"Khowai","state":"TRIPURA","offices":["Durgapur B.O","Paschim Santinagar B.O","Ramdayal Lendless Colony B.O"],"officeCount":15},{"pin":"799204","district":"Dhalai","state":"TRIPURA","offices":["Balarambazar B.O","Nalicherra B.O","Kulaibazar S.O"],"officeCount":3},{"pin":"799205","district":"Khowai","state":"TRIPURA","offices":["Ataromura B.O","Barmura Project B.O","Hadrai B.O"],"officeCount":19},{"pin":"799207","district":"Khowai","state":"TRIPURA","offices":["Rajnagar Khowai B.O","Chebri S.O","Chankhala B.O"],"officeCount":12},{"pin":"799210","district":"West Tripura","state":"TRIPURA","offices":["Chechuria B.O","Bodhjungnagar B.O","Laifunga B.O"],"officeCount":8},{"pin":"799211","district":"West Tripura","state":"TRIPURA","offices":["Baikunthapur B.O","Chachubazar B.O","Kalacherra T.E. B.O"],"officeCount":16},{"pin":"799212","district":"West Tripura","state":"TRIPURA","offices":["Darogamura B.O","Ishanpur B.O","Uttar Dasgharia B.O"],"officeCount":9},{"pin":"799250","district":"North Tripura","state":"TRIPURA","offices":["Dharmanagar H.O"],"officeCount":1},{"pin":"799251","district":"North Tripura","state":"TRIPURA","offices":["Bakbaki B.O","Baruakandi B.O","Bhagyapur B.O"],"officeCount":17},{"pin":"799253","district":"North Tripura","state":"TRIPURA","offices":["Dharmanagar Bazar B.O","East Huruah B.O","Kameswargaon B.O"],"officeCount":17},{"pin":"799254","district":"North Tripura","state":"TRIPURA","offices":["Baithangbari B.O","Jubarajnagar B.O","Paschim Radhapur B.O"],"officeCount":7},{"pin":"799256","district":"North Tripura","state":"TRIPURA","offices":["Kacharicherra B.O","Khedacherra B.O","Narendranagar B.O"],"officeCount":5},{"pin":"799260","district":"North Tripura","state":"TRIPURA","offices":["Agnipassa B.O","Indurail B.O","Padmabil B.O"],"officeCount":20},{"pin":"799261","district":"North Tripura","state":"TRIPURA","offices":["Pearacherra B.O","Kadamtala S.O (North Tripura)","Kurit B.O"],"officeCount":11},{"pin":"799262","district":"North Tripura","state":"TRIPURA","offices":["Kheranjuri B.O","Sanicherra B.O","Churaibari S.O"],"officeCount":5},{"pin":"799263","district":"Unakoti","state":"TRIPURA","offices":["Ugalcherra B.O","Dhanicherra B.O","Govidabari B.O"],"officeCount":11},{"pin":"799264","district":"Unakoti","state":"TRIPURA","offices":["East Kanchanbari B.O","Pabiacherra B.O","South Unokoti B.O"],"officeCount":8},{"pin":"799266","district":"Dhalai","state":"TRIPURA","offices":["West Nalkata B.O","Purba Betcherra B.O","Kanchancherra"],"officeCount":5},{"pin":"799269","district":"North Tripura","state":"TRIPURA","offices":["Hmungchuan B.O","Sabual B.O","Phuldengsai B.O"],"officeCount":12},{"pin":"799270","district":"North Tripura","state":"TRIPURA","offices":["Kanchanpur S.O (North Tripura)","Sibnagar B.O","Satnala B.O"],"officeCount":6},{"pin":"799271","district":"North Tripura","state":"TRIPURA","offices":["Dasdabazar S.O","Barhaldi B.O","Kalapania B.O"],"officeCount":7},{"pin":"799273","district":"Dhalai","state":"TRIPURA","offices":["Bindulal Karbaripara B.O","Durgacherra B.O","Manikpur B.O"],"officeCount":9},{"pin":"799275","district":"Dhalai","state":"TRIPURA","offices":["East Masli B.O","Jamircherra B.O","Longtharai B.O"],"officeCount":10},{"pin":"799277","district":"Unakoti","state":"TRIPURA","offices":["Manuvelly B.O","Noorpur B.O","Sadhanasram B.O"],"officeCount":15},{"pin":"799278","district":"Dhalai","state":"TRIPURA","offices":["Salema S.O","Paschim Dalucherra B.O","Kachucherra B.O"],"officeCount":6},{"pin":"799279","district":"Unakoti","state":"TRIPURA","offices":["Zarultali B.O","Chantail B.O","Deora Cherra B.O"],"officeCount":6},{"pin":"799280","district":"Unakoti","state":"TRIPURA","offices":["Birchandranagar B.O","Dalugaon B.O","Dhanbilash B.O"],"officeCount":8},{"pin":"799281","district":"Unakoti","state":"TRIPURA","offices":["Irani B.O","Rangauti B.O","Tripura Tillabazar B.O"],"officeCount":6},{"pin":"799282","district":"Unakoti","state":"TRIPURA","offices":["Gournagar SO","Chinibagan B.O","Bhagabannagar B.O"],"officeCount":3},{"pin":"799284","district":"Dhalai","state":"TRIPURA","offices":["Jagabandhu Para B.O","Laxmipur B.O","PURBA KALYANSINGPARA B.O"],"officeCount":11},{"pin":"799285","district":"Dhalai","state":"TRIPURA","offices":["Garodtilla B.O","Maracherra B.O","Noagoan B.O"],"officeCount":10},{"pin":"799286","district":"Dhalai","state":"TRIPURA","offices":["Durga Chowmuhani BO","Halahali S.O","Abhanga B.O"],"officeCount":9},{"pin":"799287","district":"Dhalai","state":"TRIPURA","offices":["Nagbangshi B.O","Srirampur Lambucherra B.O","Kamalpur Aerodrome B.O"],"officeCount":5},{"pin":"799288","district":"Unakoti","state":"TRIPURA","offices":["Kanchanbari S.O","Ujan Dodhpur B.O","Dengdung B.O"],"officeCount":8},{"pin":"799289","district":"Dhalai","state":"TRIPURA","offices":["Harincherra B.O","Kanchanpur Colony B.O","Lakraichowdhuripara B.O"],"officeCount":14},{"pin":"799290","district":"Unakoti","state":"TRIPURA","offices":["Emrapassa B.O","Gakulnagar B.O","Rajkandi B.O"],"officeCount":14}]}